setup.cfg
setup.py
triangula/__init__.py
triangula/arduino.py
triangula/chassis.py
triangula/dynamics.py
triangula/imu.py
triangula/input.py
triangula/lcd.py
triangula/sensors.py
triangula/task.py
triangula/util.py
triangula.egg-info/PKG-INFO
triangula.egg-info/SOURCES.txt
triangula.egg-info/dependency_links.txt
triangula.egg-info/not-zip-safe
triangula.egg-info/requires.txt
triangula.egg-info/top_level.txt