Metadata-Version: 1.1
Name: triangula
Version: 0.3.1
Summary: Code for Triangula
Home-page: https://github.com/tomoinn/triangula/
Author: Tom Oinn
Author-email: tomoinn@gmail.com
License: ASL2.0
Platform: UNKNOWN
Classifier: Programming Language :: Python :: 2.7
